{
  "timestamp": "2025-12-21T16:34:27.091632+00:00",
  "webhook_server": {
    "online": true,
    "health": {
      "last_heartbeat_seconds_ago": 61.6,
      "last_heartbeat_timestamp": "2025-12-21T16:33:25.446729+00:00"
    },
    "pipeline_status": null,
    "error": null
  },
  "system": {
    "uptime_seconds": 173658.37,
    "cpu_percent": 2.5,
    "memory_percent": 10.2,
    "disk_percent": 19.8,
    "disk_free_gb": 44.719085693359375,
    "timestamp": "2025-12-21T11:34:27.092083"
  },
  "activity": {
    "last_report": {
      "filename": "report_20251219_234607.html",
      "timestamp": "2025-12-19T18:46:20.068596"
    },
    "last_pipeline_run": null,
    "total_reports": 25
  },
  "recent_log": [
    "2025-12-21 11:34:25,380 - services.git_monitor - INFO - Checking repository for new commits (interval: 15s)",
    "2025-12-21 11:34:18,543 - services.web_repo_monitor - INFO - No new commits found",
    "2025-12-21 11:34:14,338 - services.web_repo_monitor - INFO - Checking web repository for new commits (interval: 15s)",
    "2025-12-21 11:34:10,380 - services.git_monitor - INFO - No new commits found",
    "2025-12-21 11:34:06,346 - services.git_monitor - INFO - Checking repository for new commits (interval: 15s)",
    "2025-12-21 11:33:59,338 - services.web_repo_monitor - INFO - No new commits found",
    "2025-12-21 11:33:55,075 - services.web_repo_monitor - INFO - Checking web repository for new commits (interval: 15s)",
    "2025-12-21 11:33:51,345 - services.git_monitor - INFO - No new commits found",
    "2025-12-21 11:33:46,903 - services.git_monitor - INFO - Checking repository for new commits (interval: 15s)",
    "2025-12-21 11:33:40,074 - services.web_repo_monitor - INFO - No new commits found",
    "2025-12-21 11:33:35,756 - services.web_repo_monitor - INFO - Checking web repository for new commits (interval: 15s)",
    "2025-12-21 11:33:31,903 - services.git_monitor - INFO - No new commits found",
    "2025-12-21 11:33:27,802 - services.git_monitor - INFO - Checking repository for new commits (interval: 15s)",
    "2025-12-21 11:33:20,755 - services.web_repo_monitor - INFO - No new commits found",
    "2025-12-21 11:33:16,690 - services.web_repo_monitor - INFO - Checking web repository for new commits (interval: 15s)",
    "2025-12-21 11:33:12,802 - services.git_monitor - INFO - No new commits found",
    "2025-12-21 11:33:07,149 - services.git_monitor - INFO - Checking repository for new commits (interval: 15s)",
    "2025-12-21 11:33:01,689 - services.web_repo_monitor - INFO - No new commits found",
    "2025-12-21 11:32:57,399 - services.web_repo_monitor - INFO - Checking web repository for new commits (interval: 15s)",
    "2025-12-21 11:32:52,148 - services.git_monitor - INFO - No new commits found"
  ]
}