{
  "timestamp": "2025-12-19T22:52:06.592223+00:00",
  "webhook_server": {
    "online": true,
    "health": {
      "last_heartbeat_seconds_ago": 60.8,
      "last_heartbeat_timestamp": "2025-12-19T22:51:05.839543+00:00"
    },
    "pipeline_status": null,
    "error": null
  },
  "system": {
    "uptime_seconds": 23517.87,
    "cpu_percent": 9.8,
    "memory_percent": 8.8,
    "disk_percent": 19.7,
    "disk_free_gb": 44.797157287597656,
    "timestamp": "2025-12-19T17:52:06.592668"
  },
  "activity": {
    "last_report": {
      "filename": "report_20251219_172514.html",
      "timestamp": "2025-12-19T12:25:25.799082"
    },
    "last_pipeline_run": null,
    "total_reports": 24
  },
  "recent_log": [
    "2025-12-19 17:52:04,926 - services.web_repo_monitor - INFO - Checking web repository for new commits (interval: 15s)",
    "2025-12-19 17:52:04,891 - services.git_monitor - INFO - Checking repository for new commits (interval: 15s)",
    "2025-12-19 17:51:49,926 - services.web_repo_monitor - INFO - No new commits found",
    "2025-12-19 17:51:49,890 - services.git_monitor - INFO - No new commits found",
    "2025-12-19 17:51:45,757 - services.web_repo_monitor - INFO - Checking web repository for new commits (interval: 15s)",
    "2025-12-19 17:51:45,461 - services.git_monitor - INFO - Checking repository for new commits (interval: 15s)",
    "2025-12-19 17:51:30,757 - services.web_repo_monitor - INFO - No new commits found",
    "2025-12-19 17:51:30,461 - services.git_monitor - INFO - No new commits found",
    "2025-12-19 17:51:26,604 - services.web_repo_monitor - INFO - Checking web repository for new commits (interval: 15s)",
    "2025-12-19 17:51:26,415 - services.git_monitor - INFO - Checking repository for new commits (interval: 15s)",
    "2025-12-19 17:51:11,603 - services.web_repo_monitor - INFO - No new commits found",
    "2025-12-19 17:51:11,414 - services.git_monitor - INFO - No new commits found",
    "2025-12-19 17:51:07,187 - services.git_monitor - INFO - Checking repository for new commits (interval: 15s)",
    "2025-12-19 17:51:07,154 - services.web_repo_monitor - INFO - Checking web repository for new commits (interval: 15s)",
    "2025-12-19 17:50:52,187 - services.git_monitor - INFO - No new commits found",
    "2025-12-19 17:50:52,154 - services.web_repo_monitor - INFO - No new commits found",
    "2025-12-19 17:50:47,791 - services.git_monitor - INFO - Checking repository for new commits (interval: 15s)",
    "2025-12-19 17:50:47,688 - services.web_repo_monitor - INFO - Checking web repository for new commits (interval: 15s)",
    "2025-12-19 17:50:32,791 - services.git_monitor - INFO - No new commits found",
    "2025-12-19 17:50:32,687 - services.web_repo_monitor - INFO - No new commits found"
  ]
}