{
  "timestamp": "2025-12-19T20:51:25.075111+00:00",
  "webhook_server": {
    "online": true,
    "health": {
      "last_heartbeat_seconds_ago": 60.6,
      "last_heartbeat_timestamp": "2025-12-19T20:50:24.435518+00:00"
    },
    "pipeline_status": null,
    "error": null
  },
  "system": {
    "uptime_seconds": 16276.35,
    "cpu_percent": 0.3,
    "memory_percent": 24.7,
    "disk_percent": 19.7,
    "disk_free_gb": 44.79903030395508,
    "timestamp": "2025-12-19T15:51:25.075565"
  },
  "activity": {
    "last_report": {
      "filename": "report_20251219_172514.html",
      "timestamp": "2025-12-19T12:25:25.799082"
    },
    "last_pipeline_run": null,
    "total_reports": 24
  },
  "recent_log": [
    "2025-12-19 15:51:24,867 - services.git_monitor - INFO - No new commits found",
    "2025-12-19 15:51:20,563 - services.git_monitor - INFO - Checking repository for new commits (interval: 15s)",
    "2025-12-19 15:51:13,834 - services.web_repo_monitor - INFO - No new commits found",
    "2025-12-19 15:51:09,407 - services.web_repo_monitor - INFO - Checking web repository for new commits (interval: 15s)",
    "2025-12-19 15:51:05,562 - services.git_monitor - INFO - No new commits found",
    "2025-12-19 15:51:01,341 - services.git_monitor - INFO - Checking repository for new commits (interval: 15s)",
    "2025-12-19 15:50:54,406 - services.web_repo_monitor - INFO - No new commits found",
    "2025-12-19 15:50:49,980 - services.web_repo_monitor - INFO - Checking web repository for new commits (interval: 15s)",
    "2025-12-19 15:50:46,341 - services.git_monitor - INFO - No new commits found",
    "2025-12-19 15:50:42,023 - services.git_monitor - INFO - Checking repository for new commits (interval: 15s)",
    "2025-12-19 15:50:34,979 - services.web_repo_monitor - INFO - No new commits found",
    "2025-12-19 15:50:30,911 - services.web_repo_monitor - INFO - Checking web repository for new commits (interval: 15s)",
    "2025-12-19 15:50:27,023 - services.git_monitor - INFO - No new commits found",
    "2025-12-19 15:50:22,675 - services.git_monitor - INFO - Checking repository for new commits (interval: 15s)",
    "2025-12-19 15:50:15,910 - services.web_repo_monitor - INFO - No new commits found",
    "2025-12-19 15:50:11,743 - services.web_repo_monitor - INFO - Checking web repository for new commits (interval: 15s)",
    "2025-12-19 15:50:07,674 - services.git_monitor - INFO - No new commits found",
    "2025-12-19 15:50:03,299 - services.git_monitor - INFO - Checking repository for new commits (interval: 15s)",
    "2025-12-19 15:49:56,743 - services.web_repo_monitor - INFO - No new commits found",
    "2025-12-19 15:49:52,477 - services.web_repo_monitor - INFO - Checking web repository for new commits (interval: 15s)"
  ]
}