{
  "timestamp": "2025-12-20T05:57:04.051466+00:00",
  "webhook_server": {
    "online": true,
    "health": {
      "last_heartbeat_seconds_ago": 63.2,
      "last_heartbeat_timestamp": "2025-12-20T05:56:00.834627+00:00"
    },
    "pipeline_status": null,
    "error": null
  },
  "system": {
    "uptime_seconds": 49015.33,
    "cpu_percent": 7.7,
    "memory_percent": 9.5,
    "disk_percent": 19.8,
    "disk_free_gb": 44.73027420043945,
    "timestamp": "2025-12-20T00:57:04.051909"
  },
  "activity": {
    "last_report": {
      "filename": "report_20251219_234607.html",
      "timestamp": "2025-12-19T18:46:20.068596"
    },
    "last_pipeline_run": null,
    "total_reports": 25
  },
  "recent_log": [
    "2025-12-20 00:57:02,437 - services.web_repo_monitor - INFO - Checking web repository for new commits (interval: 15s)",
    "2025-12-20 00:57:00,600 - services.git_monitor - INFO - No new commits found",
    "2025-12-20 00:56:56,558 - services.git_monitor - INFO - Checking repository for new commits (interval: 15s)",
    "2025-12-20 00:56:47,437 - services.web_repo_monitor - INFO - No new commits found",
    "2025-12-20 00:56:43,451 - services.web_repo_monitor - INFO - Checking web repository for new commits (interval: 15s)",
    "2025-12-20 00:56:41,557 - services.git_monitor - INFO - No new commits found",
    "2025-12-20 00:56:37,552 - services.git_monitor - INFO - Checking repository for new commits (interval: 15s)",
    "2025-12-20 00:56:28,451 - services.web_repo_monitor - INFO - No new commits found",
    "2025-12-20 00:56:24,087 - services.web_repo_monitor - INFO - Checking web repository for new commits (interval: 15s)",
    "2025-12-20 00:56:22,552 - services.git_monitor - INFO - No new commits found",
    "2025-12-20 00:56:18,449 - services.git_monitor - INFO - Checking repository for new commits (interval: 15s)",
    "2025-12-20 00:56:09,087 - services.web_repo_monitor - INFO - No new commits found",
    "2025-12-20 00:56:05,069 - services.web_repo_monitor - INFO - Checking web repository for new commits (interval: 15s)",
    "2025-12-20 00:56:03,448 - services.git_monitor - INFO - No new commits found",
    "2025-12-20 00:55:59,154 - services.git_monitor - INFO - Checking repository for new commits (interval: 15s)",
    "2025-12-20 00:55:50,069 - services.web_repo_monitor - INFO - No new commits found",
    "2025-12-20 00:55:46,055 - services.web_repo_monitor - INFO - Checking web repository for new commits (interval: 15s)",
    "2025-12-20 00:55:44,154 - services.git_monitor - INFO - No new commits found",
    "2025-12-20 00:55:37,479 - services.git_monitor - INFO - Checking repository for new commits (interval: 15s)",
    "2025-12-20 00:55:31,055 - services.web_repo_monitor - INFO - No new commits found"
  ]
}