{
  "timestamp": "2025-12-19T23:20:27.490909+00:00",
  "webhook_server": {
    "online": true,
    "health": {
      "last_heartbeat_seconds_ago": 65.0,
      "last_heartbeat_timestamp": "2025-12-19T23:19:22.484610+00:00"
    },
    "pipeline_status": null,
    "error": null
  },
  "system": {
    "uptime_seconds": 25218.77,
    "cpu_percent": 7.5,
    "memory_percent": 8.7,
    "disk_percent": 19.7,
    "disk_free_gb": 44.79673385620117,
    "timestamp": "2025-12-19T18:20:27.491348"
  },
  "activity": {
    "last_report": {
      "filename": "report_20251219_172514.html",
      "timestamp": "2025-12-19T12:25:25.799082"
    },
    "last_pipeline_run": null,
    "total_reports": 24
  },
  "recent_log": [
    "2025-12-19 18:20:28,092 - services.git_monitor - INFO - Checking repository for new commits (interval: 15s)",
    "2025-12-19 18:20:27,047 - services.web_repo_monitor - INFO - Checking web repository for new commits (interval: 15s)",
    "2025-12-19 18:20:13,092 - services.git_monitor - INFO - No new commits found",
    "2025-12-19 18:20:12,046 - services.web_repo_monitor - INFO - No new commits found",
    "2025-12-19 18:20:07,031 - services.git_monitor - INFO - Checking repository for new commits (interval: 15s)",
    "2025-12-19 18:20:05,782 - services.web_repo_monitor - INFO - Checking web repository for new commits (interval: 15s)",
    "2025-12-19 18:19:52,030 - services.git_monitor - INFO - No new commits found",
    "2025-12-19 18:19:50,782 - services.web_repo_monitor - INFO - No new commits found",
    "2025-12-19 18:19:45,016 - services.git_monitor - INFO - Checking repository for new commits (interval: 15s)",
    "2025-12-19 18:19:43,664 - services.web_repo_monitor - INFO - Checking web repository for new commits (interval: 15s)",
    "2025-12-19 18:19:30,016 - services.git_monitor - INFO - No new commits found",
    "2025-12-19 18:19:28,664 - services.web_repo_monitor - INFO - No new commits found",
    "2025-12-19 18:19:21,989 - services.git_monitor - INFO - Checking repository for new commits (interval: 15s)",
    "2025-12-19 18:19:20,287 - services.web_repo_monitor - INFO - Checking web repository for new commits (interval: 15s)",
    "2025-12-19 18:19:06,988 - services.git_monitor - INFO - No new commits found",
    "2025-12-19 18:19:05,287 - services.web_repo_monitor - INFO - No new commits found",
    "2025-12-19 18:19:00,762 - services.git_monitor - INFO - Checking repository for new commits (interval: 15s)",
    "2025-12-19 18:18:58,353 - services.web_repo_monitor - INFO - Checking web repository for new commits (interval: 15s)",
    "2025-12-19 18:18:45,761 - services.git_monitor - INFO - No new commits found",
    "2025-12-19 18:18:43,352 - services.web_repo_monitor - INFO - No new commits found"
  ]
}