{
  "timestamp": "2025-12-20T16:26:46.557155+00:00",
  "webhook_server": {
    "online": true,
    "health": {
      "last_heartbeat_seconds_ago": 61.9,
      "last_heartbeat_timestamp": "2025-12-20T16:25:44.610758+00:00"
    },
    "pipeline_status": null,
    "error": null
  },
  "system": {
    "uptime_seconds": 86797.84,
    "cpu_percent": 0.5,
    "memory_percent": 9.7,
    "disk_percent": 19.8,
    "disk_free_gb": 44.72076416015625,
    "timestamp": "2025-12-20T11:26:46.557608"
  },
  "activity": {
    "last_report": {
      "filename": "report_20251219_234607.html",
      "timestamp": "2025-12-19T18:46:20.068596"
    },
    "last_pipeline_run": null,
    "total_reports": 25
  },
  "recent_log": [
    "2025-12-20 11:26:39,629 - services.web_repo_monitor - INFO - No new commits found",
    "2025-12-20 11:26:35,575 - services.web_repo_monitor - INFO - Checking web repository for new commits (interval: 15s)",
    "2025-12-20 11:26:35,091 - services.git_monitor - INFO - No new commits found",
    "2025-12-20 11:26:30,535 - services.git_monitor - INFO - Checking repository for new commits (interval: 15s)",
    "2025-12-20 11:26:20,575 - services.web_repo_monitor - INFO - No new commits found",
    "2025-12-20 11:26:16,404 - services.web_repo_monitor - INFO - Checking web repository for new commits (interval: 15s)",
    "2025-12-20 11:26:15,535 - services.git_monitor - INFO - No new commits found",
    "2025-12-20 11:26:11,176 - services.git_monitor - INFO - Checking repository for new commits (interval: 15s)",
    "2025-12-20 11:26:01,404 - services.web_repo_monitor - INFO - No new commits found",
    "2025-12-20 11:25:57,369 - services.web_repo_monitor - INFO - Checking web repository for new commits (interval: 15s)",
    "2025-12-20 11:25:56,176 - services.git_monitor - INFO - No new commits found",
    "2025-12-20 11:25:52,047 - services.git_monitor - INFO - Checking repository for new commits (interval: 15s)",
    "2025-12-20 11:25:42,368 - services.web_repo_monitor - INFO - No new commits found",
    "2025-12-20 11:25:38,454 - services.web_repo_monitor - INFO - Checking web repository for new commits (interval: 15s)",
    "2025-12-20 11:25:37,046 - services.git_monitor - INFO - No new commits found",
    "2025-12-20 11:25:32,623 - services.git_monitor - INFO - Checking repository for new commits (interval: 15s)",
    "2025-12-20 11:25:23,453 - services.web_repo_monitor - INFO - No new commits found",
    "2025-12-20 11:25:19,648 - services.web_repo_monitor - INFO - Checking web repository for new commits (interval: 15s)",
    "2025-12-20 11:25:17,623 - services.git_monitor - INFO - No new commits found",
    "2025-12-20 11:25:13,423 - services.git_monitor - INFO - Checking repository for new commits (interval: 15s)"
  ]
}