{
  "timestamp": "2025-12-21T04:25:17.782820+00:00",
  "webhook_server": {
    "online": true,
    "health": {
      "last_heartbeat_seconds_ago": 60.6,
      "last_heartbeat_timestamp": "2025-12-21T04:24:17.170225+00:00"
    },
    "pipeline_status": null,
    "error": null
  },
  "system": {
    "uptime_seconds": 129909.06,
    "cpu_percent": 11.3,
    "memory_percent": 10.0,
    "disk_percent": 19.8,
    "disk_free_gb": 44.73020553588867,
    "timestamp": "2025-12-20T23:25:17.783337"
  },
  "activity": {
    "last_report": {
      "filename": "report_20251219_234607.html",
      "timestamp": "2025-12-19T18:46:20.068596"
    },
    "last_pipeline_run": null,
    "total_reports": 25
  },
  "recent_log": [
    "2025-12-20 23:25:17,514 - services.web_repo_monitor - INFO - Checking web repository for new commits (interval: 15s)",
    "2025-12-20 23:25:15,026 - services.git_monitor - INFO - Checking repository for new commits (interval: 15s)",
    "2025-12-20 23:25:02,514 - services.web_repo_monitor - INFO - No new commits found",
    "2025-12-20 23:25:00,025 - services.git_monitor - INFO - No new commits found",
    "2025-12-20 23:24:58,450 - services.web_repo_monitor - INFO - Checking web repository for new commits (interval: 15s)",
    "2025-12-20 23:24:55,585 - services.git_monitor - INFO - Checking repository for new commits (interval: 15s)",
    "2025-12-20 23:24:43,450 - services.web_repo_monitor - INFO - No new commits found",
    "2025-12-20 23:24:40,584 - services.git_monitor - INFO - No new commits found",
    "2025-12-20 23:24:39,384 - services.web_repo_monitor - INFO - Checking web repository for new commits (interval: 15s)",
    "2025-12-20 23:24:36,371 - services.git_monitor - INFO - Checking repository for new commits (interval: 15s)",
    "2025-12-20 23:24:24,384 - services.web_repo_monitor - INFO - No new commits found",
    "2025-12-20 23:24:21,371 - services.git_monitor - INFO - No new commits found",
    "2025-12-20 23:24:20,357 - services.web_repo_monitor - INFO - Checking web repository for new commits (interval: 15s)",
    "2025-12-20 23:24:17,017 - services.git_monitor - INFO - Checking repository for new commits (interval: 15s)",
    "2025-12-20 23:24:05,357 - services.web_repo_monitor - INFO - No new commits found",
    "2025-12-20 23:24:02,016 - services.git_monitor - INFO - No new commits found",
    "2025-12-20 23:24:00,694 - services.web_repo_monitor - INFO - Checking web repository for new commits (interval: 15s)",
    "2025-12-20 23:23:57,578 - services.git_monitor - INFO - Checking repository for new commits (interval: 15s)",
    "2025-12-20 23:23:45,694 - services.web_repo_monitor - INFO - No new commits found",
    "2025-12-20 23:23:42,577 - services.git_monitor - INFO - No new commits found"
  ]
}