{
  "timestamp": "2025-12-21T11:24:35.256247+00:00",
  "webhook_server": {
    "online": true,
    "health": {
      "last_heartbeat_seconds_ago": 60.7,
      "last_heartbeat_timestamp": "2025-12-21T11:23:34.585406+00:00"
    },
    "pipeline_status": null,
    "error": null
  },
  "system": {
    "uptime_seconds": 155066.54,
    "cpu_percent": 0.0,
    "memory_percent": 10.0,
    "disk_percent": 19.8,
    "disk_free_gb": 44.72377395629883,
    "timestamp": "2025-12-21T06:24:35.256748"
  },
  "activity": {
    "last_report": {
      "filename": "report_20251219_234607.html",
      "timestamp": "2025-12-19T18:46:20.068596"
    },
    "last_pipeline_run": null,
    "total_reports": 25
  },
  "recent_log": [
    "2025-12-21 06:24:33,837 - services.web_repo_monitor - INFO - No new commits found",
    "2025-12-21 06:24:31,829 - services.git_monitor - INFO - No new commits found",
    "2025-12-21 06:24:29,224 - services.web_repo_monitor - INFO - Checking web repository for new commits (interval: 15s)",
    "2025-12-21 06:24:27,449 - services.git_monitor - INFO - Checking repository for new commits (interval: 15s)",
    "2025-12-21 06:24:14,224 - services.web_repo_monitor - INFO - No new commits found",
    "2025-12-21 06:24:12,448 - services.git_monitor - INFO - No new commits found",
    "2025-12-21 06:24:09,916 - services.web_repo_monitor - INFO - Checking web repository for new commits (interval: 15s)",
    "2025-12-21 06:24:08,321 - services.git_monitor - INFO - Checking repository for new commits (interval: 15s)",
    "2025-12-21 06:23:54,913 - services.web_repo_monitor - INFO - No new commits found",
    "2025-12-21 06:23:53,320 - services.git_monitor - INFO - No new commits found",
    "2025-12-21 06:23:50,719 - services.web_repo_monitor - INFO - Checking web repository for new commits (interval: 15s)",
    "2025-12-21 06:23:49,205 - services.git_monitor - INFO - Checking repository for new commits (interval: 15s)",
    "2025-12-21 06:23:35,718 - services.web_repo_monitor - INFO - No new commits found",
    "2025-12-21 06:23:34,204 - services.git_monitor - INFO - No new commits found",
    "2025-12-21 06:23:31,642 - services.web_repo_monitor - INFO - Checking web repository for new commits (interval: 15s)",
    "2025-12-21 06:23:29,832 - services.git_monitor - INFO - Checking repository for new commits (interval: 15s)",
    "2025-12-21 06:23:16,641 - services.web_repo_monitor - INFO - No new commits found",
    "2025-12-21 06:23:14,831 - services.git_monitor - INFO - No new commits found",
    "2025-12-21 06:23:12,456 - services.web_repo_monitor - INFO - Checking web repository for new commits (interval: 15s)",
    "2025-12-21 06:23:10,745 - services.git_monitor - INFO - Checking repository for new commits (interval: 15s)"
  ]
}