{
  "timestamp": "2025-12-20T00:08:54.863008+00:00",
  "webhook_server": {
    "online": true,
    "health": {
      "last_heartbeat_seconds_ago": 60.0,
      "last_heartbeat_timestamp": "2025-12-20T00:07:54.845275+00:00"
    },
    "pipeline_status": null,
    "error": null
  },
  "system": {
    "uptime_seconds": 28126.14,
    "cpu_percent": 5.8,
    "memory_percent": 9.5,
    "disk_percent": 19.8,
    "disk_free_gb": 44.73578643798828,
    "timestamp": "2025-12-19T19:08:54.863459"
  },
  "activity": {
    "last_report": {
      "filename": "report_20251219_234607.html",
      "timestamp": "2025-12-19T18:46:20.068596"
    },
    "last_pipeline_run": null,
    "total_reports": 25
  },
  "recent_log": [
    "2025-12-19 19:08:55,088 - services.web_repo_monitor - INFO - No new commits found",
    "2025-12-19 19:08:52,982 - services.git_monitor - INFO - Checking repository for new commits (interval: 15s)",
    "2025-12-19 19:08:50,818 - services.web_repo_monitor - INFO - Checking web repository for new commits (interval: 15s)",
    "2025-12-19 19:08:37,982 - services.git_monitor - INFO - No new commits found",
    "2025-12-19 19:08:35,818 - services.web_repo_monitor - INFO - No new commits found",
    "2025-12-19 19:08:34,032 - services.git_monitor - INFO - Checking repository for new commits (interval: 15s)",
    "2025-12-19 19:08:31,739 - services.web_repo_monitor - INFO - Checking web repository for new commits (interval: 15s)",
    "2025-12-19 19:08:19,032 - services.git_monitor - INFO - No new commits found",
    "2025-12-19 19:08:16,739 - services.web_repo_monitor - INFO - No new commits found",
    "2025-12-19 19:08:14,663 - services.git_monitor - INFO - Checking repository for new commits (interval: 15s)",
    "2025-12-19 19:08:12,737 - services.web_repo_monitor - INFO - Checking web repository for new commits (interval: 15s)",
    "2025-12-19 19:07:59,662 - services.git_monitor - INFO - No new commits found",
    "2025-12-19 19:07:57,737 - services.web_repo_monitor - INFO - No new commits found",
    "2025-12-19 19:07:55,148 - services.git_monitor - INFO - Checking repository for new commits (interval: 15s)",
    "2025-12-19 19:07:53,726 - services.web_repo_monitor - INFO - Checking web repository for new commits (interval: 15s)",
    "2025-12-19 19:07:40,147 - services.git_monitor - INFO - No new commits found",
    "2025-12-19 19:07:38,726 - services.web_repo_monitor - INFO - No new commits found",
    "2025-12-19 19:07:35,809 - services.git_monitor - INFO - Checking repository for new commits (interval: 15s)",
    "2025-12-19 19:07:34,380 - services.web_repo_monitor - INFO - Checking web repository for new commits (interval: 15s)",
    "2025-12-19 19:07:20,809 - services.git_monitor - INFO - No new commits found"
  ]
}