{
  "timestamp": "2025-12-20T18:48:39.100524+00:00",
  "webhook_server": {
    "online": true,
    "health": {
      "last_heartbeat_seconds_ago": 60.4,
      "last_heartbeat_timestamp": "2025-12-20T18:47:38.731672+00:00"
    },
    "pipeline_status": null,
    "error": null
  },
  "system": {
    "uptime_seconds": 95310.38,
    "cpu_percent": 4.5,
    "memory_percent": 9.8,
    "disk_percent": 19.8,
    "disk_free_gb": 44.71864318847656,
    "timestamp": "2025-12-20T13:48:39.101023"
  },
  "activity": {
    "last_report": {
      "filename": "report_20251219_234607.html",
      "timestamp": "2025-12-19T18:46:20.068596"
    },
    "last_pipeline_run": null,
    "total_reports": 25
  },
  "recent_log": [
    "2025-12-20 13:48:38,946 - services.git_monitor - INFO - No new commits found",
    "2025-12-20 13:48:38,874 - services.web_repo_monitor - INFO - No new commits found",
    "2025-12-20 13:48:34,792 - services.git_monitor - INFO - Checking repository for new commits (interval: 15s)",
    "2025-12-20 13:48:34,697 - services.web_repo_monitor - INFO - Checking web repository for new commits (interval: 15s)",
    "2025-12-20 13:48:19,792 - services.git_monitor - INFO - No new commits found",
    "2025-12-20 13:48:19,696 - services.web_repo_monitor - INFO - No new commits found",
    "2025-12-20 13:48:15,626 - services.web_repo_monitor - INFO - Checking web repository for new commits (interval: 15s)",
    "2025-12-20 13:48:15,439 - services.git_monitor - INFO - Checking repository for new commits (interval: 15s)",
    "2025-12-20 13:48:00,625 - services.web_repo_monitor - INFO - No new commits found",
    "2025-12-20 13:48:00,438 - services.git_monitor - INFO - No new commits found",
    "2025-12-20 13:47:56,671 - services.git_monitor - INFO - Checking repository for new commits (interval: 15s)",
    "2025-12-20 13:47:56,435 - services.web_repo_monitor - INFO - Checking web repository for new commits (interval: 15s)",
    "2025-12-20 13:47:41,671 - services.git_monitor - INFO - No new commits found",
    "2025-12-20 13:47:41,435 - services.web_repo_monitor - INFO - No new commits found",
    "2025-12-20 13:47:37,707 - services.git_monitor - INFO - Checking repository for new commits (interval: 15s)",
    "2025-12-20 13:47:36,735 - services.web_repo_monitor - INFO - Checking web repository for new commits (interval: 15s)",
    "2025-12-20 13:47:22,701 - services.git_monitor - INFO - No new commits found",
    "2025-12-20 13:47:21,734 - services.web_repo_monitor - INFO - No new commits found",
    "2025-12-20 13:47:18,264 - services.git_monitor - INFO - Checking repository for new commits (interval: 15s)",
    "2025-12-20 13:47:17,673 - services.web_repo_monitor - INFO - Checking web repository for new commits (interval: 15s)"
  ]
}