{
  "timestamp": "2025-12-20T06:34:38.288898+00:00",
  "webhook_server": {
    "online": true,
    "health": {
      "last_heartbeat_seconds_ago": 63.5,
      "last_heartbeat_timestamp": "2025-12-20T06:33:34.808033+00:00"
    },
    "pipeline_status": null,
    "error": null
  },
  "system": {
    "uptime_seconds": 51269.57,
    "cpu_percent": 7.0,
    "memory_percent": 9.5,
    "disk_percent": 19.8,
    "disk_free_gb": 44.72970962524414,
    "timestamp": "2025-12-20T01:34:38.289357"
  },
  "activity": {
    "last_report": {
      "filename": "report_20251219_234607.html",
      "timestamp": "2025-12-19T18:46:20.068596"
    },
    "last_pipeline_run": null,
    "total_reports": 25
  },
  "recent_log": [
    "2025-12-20 01:34:36,673 - services.web_repo_monitor - INFO - Checking web repository for new commits (interval: 15s)",
    "2025-12-20 01:34:29,301 - services.git_monitor - INFO - No new commits found",
    "2025-12-20 01:34:25,157 - services.git_monitor - INFO - Checking repository for new commits (interval: 15s)",
    "2025-12-20 01:34:21,672 - services.web_repo_monitor - INFO - No new commits found",
    "2025-12-20 01:34:17,391 - services.web_repo_monitor - INFO - Checking web repository for new commits (interval: 15s)",
    "2025-12-20 01:34:10,157 - services.git_monitor - INFO - No new commits found",
    "2025-12-20 01:34:06,097 - services.git_monitor - INFO - Checking repository for new commits (interval: 15s)",
    "2025-12-20 01:34:02,390 - services.web_repo_monitor - INFO - No new commits found",
    "2025-12-20 01:33:58,297 - services.web_repo_monitor - INFO - Checking web repository for new commits (interval: 15s)",
    "2025-12-20 01:33:51,097 - services.git_monitor - INFO - No new commits found",
    "2025-12-20 01:33:46,598 - services.git_monitor - INFO - Checking repository for new commits (interval: 15s)",
    "2025-12-20 01:33:43,297 - services.web_repo_monitor - INFO - No new commits found",
    "2025-12-20 01:33:39,136 - services.web_repo_monitor - INFO - Checking web repository for new commits (interval: 15s)",
    "2025-12-20 01:33:31,598 - services.git_monitor - INFO - No new commits found",
    "2025-12-20 01:33:27,208 - services.git_monitor - INFO - Checking repository for new commits (interval: 15s)",
    "2025-12-20 01:33:24,135 - services.web_repo_monitor - INFO - No new commits found",
    "2025-12-20 01:33:19,700 - services.web_repo_monitor - INFO - Checking web repository for new commits (interval: 15s)",
    "2025-12-20 01:33:12,207 - services.git_monitor - INFO - No new commits found",
    "2025-12-20 01:33:08,052 - services.git_monitor - INFO - Checking repository for new commits (interval: 15s)",
    "2025-12-20 01:33:04,699 - services.web_repo_monitor - INFO - No new commits found"
  ]
}