{
  "timestamp": "2025-12-21T00:19:53.373073+00:00",
  "webhook_server": {
    "online": true,
    "health": {
      "last_heartbeat_seconds_ago": 61.8,
      "last_heartbeat_timestamp": "2025-12-21T00:18:51.535612+00:00"
    },
    "pipeline_status": null,
    "error": null
  },
  "system": {
    "uptime_seconds": 115184.65,
    "cpu_percent": 2.3,
    "memory_percent": 9.9,
    "disk_percent": 19.8,
    "disk_free_gb": 44.713645935058594,
    "timestamp": "2025-12-20T19:19:53.373528"
  },
  "activity": {
    "last_report": {
      "filename": "report_20251219_234607.html",
      "timestamp": "2025-12-19T18:46:20.068596"
    },
    "last_pipeline_run": null,
    "total_reports": 25
  },
  "recent_log": [
    "2025-12-20 19:19:48,948 - services.git_monitor - INFO - No new commits found",
    "2025-12-20 19:19:44,939 - services.git_monitor - INFO - Checking repository for new commits (interval: 15s)",
    "2025-12-20 19:19:44,501 - services.web_repo_monitor - INFO - No new commits found",
    "2025-12-20 19:19:40,257 - services.web_repo_monitor - INFO - Checking web repository for new commits (interval: 15s)",
    "2025-12-20 19:19:29,939 - services.git_monitor - INFO - No new commits found",
    "2025-12-20 19:19:25,460 - services.git_monitor - INFO - Checking repository for new commits (interval: 15s)",
    "2025-12-20 19:19:25,257 - services.web_repo_monitor - INFO - No new commits found",
    "2025-12-20 19:19:21,326 - services.web_repo_monitor - INFO - Checking web repository for new commits (interval: 15s)",
    "2025-12-20 19:19:10,460 - services.git_monitor - INFO - No new commits found",
    "2025-12-20 19:19:06,326 - services.web_repo_monitor - INFO - No new commits found",
    "2025-12-20 19:19:06,310 - services.git_monitor - INFO - Checking repository for new commits (interval: 15s)",
    "2025-12-20 19:19:02,062 - services.web_repo_monitor - INFO - Checking web repository for new commits (interval: 15s)",
    "2025-12-20 19:18:51,309 - services.git_monitor - INFO - No new commits found",
    "2025-12-20 19:18:47,062 - services.web_repo_monitor - INFO - No new commits found",
    "2025-12-20 19:18:46,839 - services.git_monitor - INFO - Checking repository for new commits (interval: 15s)",
    "2025-12-20 19:18:43,147 - services.web_repo_monitor - INFO - Checking web repository for new commits (interval: 15s)",
    "2025-12-20 19:18:31,839 - services.git_monitor - INFO - No new commits found",
    "2025-12-20 19:18:28,147 - services.web_repo_monitor - INFO - No new commits found",
    "2025-12-20 19:18:27,460 - services.git_monitor - INFO - Checking repository for new commits (interval: 15s)",
    "2025-12-20 19:18:23,939 - services.web_repo_monitor - INFO - Checking web repository for new commits (interval: 15s)"
  ]
}