{
  "timestamp": "2025-12-20T07:04:11.916895+00:00",
  "webhook_server": {
    "online": true,
    "health": {
      "last_heartbeat_seconds_ago": 60.7,
      "last_heartbeat_timestamp": "2025-12-20T07:03:11.224761+00:00"
    },
    "pipeline_status": null,
    "error": null
  },
  "system": {
    "uptime_seconds": 53043.2,
    "cpu_percent": 2.3,
    "memory_percent": 9.4,
    "disk_percent": 19.8,
    "disk_free_gb": 44.729251861572266,
    "timestamp": "2025-12-20T02:04:11.917352"
  },
  "activity": {
    "last_report": {
      "filename": "report_20251219_234607.html",
      "timestamp": "2025-12-19T18:46:20.068596"
    },
    "last_pipeline_run": null,
    "total_reports": 25
  },
  "recent_log": [
    "2025-12-20 02:04:04,084 - services.git_monitor - INFO - No new commits found",
    "2025-12-20 02:04:04,058 - services.web_repo_monitor - INFO - No new commits found",
    "2025-12-20 02:04:00,171 - services.web_repo_monitor - INFO - Checking web repository for new commits (interval: 15s)",
    "2025-12-20 02:03:59,685 - services.git_monitor - INFO - Checking repository for new commits (interval: 15s)",
    "2025-12-20 02:03:45,171 - services.web_repo_monitor - INFO - No new commits found",
    "2025-12-20 02:03:44,684 - services.git_monitor - INFO - No new commits found",
    "2025-12-20 02:03:40,901 - services.web_repo_monitor - INFO - Checking web repository for new commits (interval: 15s)",
    "2025-12-20 02:03:40,389 - services.git_monitor - INFO - Checking repository for new commits (interval: 15s)",
    "2025-12-20 02:03:25,901 - services.web_repo_monitor - INFO - No new commits found",
    "2025-12-20 02:03:25,388 - services.git_monitor - INFO - No new commits found",
    "2025-12-20 02:03:21,860 - services.web_repo_monitor - INFO - Checking web repository for new commits (interval: 15s)",
    "2025-12-20 02:03:21,051 - services.git_monitor - INFO - Checking repository for new commits (interval: 15s)",
    "2025-12-20 02:03:06,859 - services.web_repo_monitor - INFO - No new commits found",
    "2025-12-20 02:03:06,051 - services.git_monitor - INFO - No new commits found",
    "2025-12-20 02:03:02,823 - services.web_repo_monitor - INFO - Checking web repository for new commits (interval: 15s)",
    "2025-12-20 02:03:02,112 - services.git_monitor - INFO - Checking repository for new commits (interval: 15s)",
    "2025-12-20 02:02:47,822 - services.web_repo_monitor - INFO - No new commits found",
    "2025-12-20 02:02:47,111 - services.git_monitor - INFO - No new commits found",
    "2025-12-20 02:02:43,701 - services.web_repo_monitor - INFO - Checking web repository for new commits (interval: 15s)",
    "2025-12-20 02:02:42,634 - services.git_monitor - INFO - Checking repository for new commits (interval: 15s)"
  ]
}