{
  "timestamp": "2025-12-21T21:28:25.700137+00:00",
  "webhook_server": {
    "online": true,
    "health": {
      "last_heartbeat_seconds_ago": 60.2,
      "last_heartbeat_timestamp": "2025-12-21T21:27:25.526436+00:00"
    },
    "pipeline_status": null,
    "error": null
  },
  "system": {
    "uptime_seconds": 191296.98,
    "cpu_percent": 0.0,
    "memory_percent": 10.3,
    "disk_percent": 19.8,
    "disk_free_gb": 44.714637756347656,
    "timestamp": "2025-12-21T16:28:25.700589"
  },
  "activity": {
    "last_report": {
      "filename": "report_20251219_234607.html",
      "timestamp": "2025-12-19T18:46:20.068596"
    },
    "last_pipeline_run": null,
    "total_reports": 25
  },
  "recent_log": [
    "2025-12-21 16:28:24,339 - services.git_monitor - INFO - No new commits found",
    "2025-12-21 16:28:21,103 - services.web_repo_monitor - INFO - No new commits found",
    "2025-12-21 16:28:19,964 - services.git_monitor - INFO - Checking repository for new commits (interval: 15s)",
    "2025-12-21 16:28:16,811 - services.web_repo_monitor - INFO - Checking web repository for new commits (interval: 15s)",
    "2025-12-21 16:28:04,963 - services.git_monitor - INFO - No new commits found",
    "2025-12-21 16:28:01,811 - services.web_repo_monitor - INFO - No new commits found",
    "2025-12-21 16:28:00,795 - services.git_monitor - INFO - Checking repository for new commits (interval: 15s)",
    "2025-12-21 16:27:57,716 - services.web_repo_monitor - INFO - Checking web repository for new commits (interval: 15s)",
    "2025-12-21 16:27:45,794 - services.git_monitor - INFO - No new commits found",
    "2025-12-21 16:27:42,715 - services.web_repo_monitor - INFO - No new commits found",
    "2025-12-21 16:27:41,662 - services.git_monitor - INFO - Checking repository for new commits (interval: 15s)",
    "2025-12-21 16:27:38,569 - services.web_repo_monitor - INFO - Checking web repository for new commits (interval: 15s)",
    "2025-12-21 16:27:26,662 - services.git_monitor - INFO - No new commits found",
    "2025-12-21 16:27:23,568 - services.web_repo_monitor - INFO - No new commits found",
    "2025-12-21 16:27:22,594 - services.git_monitor - INFO - Checking repository for new commits (interval: 15s)",
    "2025-12-21 16:27:19,378 - services.web_repo_monitor - INFO - Checking web repository for new commits (interval: 15s)",
    "2025-12-21 16:27:07,594 - services.git_monitor - INFO - No new commits found",
    "2025-12-21 16:27:04,378 - services.web_repo_monitor - INFO - No new commits found",
    "2025-12-21 16:27:03,157 - services.git_monitor - INFO - Checking repository for new commits (interval: 15s)",
    "2025-12-21 16:26:58,517 - services.web_repo_monitor - INFO - Checking web repository for new commits (interval: 15s)"
  ]
}