{
  "timestamp": "2025-12-21T16:41:37.664541+00:00",
  "webhook_server": {
    "online": true,
    "health": {
      "last_heartbeat_seconds_ago": 61.8,
      "last_heartbeat_timestamp": "2025-12-21T16:40:35.877584+00:00"
    },
    "pipeline_status": null,
    "error": null
  },
  "system": {
    "uptime_seconds": 174088.94,
    "cpu_percent": 2.8,
    "memory_percent": 10.2,
    "disk_percent": 19.8,
    "disk_free_gb": 44.718971252441406,
    "timestamp": "2025-12-21T11:41:37.665041"
  },
  "activity": {
    "last_report": {
      "filename": "report_20251219_234607.html",
      "timestamp": "2025-12-19T18:46:20.068596"
    },
    "last_pipeline_run": null,
    "total_reports": 25
  },
  "recent_log": [
    "2025-12-21 11:41:35,955 - services.web_repo_monitor - INFO - Checking web repository for new commits (interval: 15s)",
    "2025-12-21 11:41:33,953 - services.git_monitor - INFO - No new commits found",
    "2025-12-21 11:41:28,995 - services.git_monitor - INFO - Checking repository for new commits (interval: 15s)",
    "2025-12-21 11:41:20,955 - services.web_repo_monitor - INFO - No new commits found",
    "2025-12-21 11:41:16,737 - services.web_repo_monitor - INFO - Checking web repository for new commits (interval: 15s)",
    "2025-12-21 11:41:13,995 - services.git_monitor - INFO - No new commits found",
    "2025-12-21 11:41:09,705 - services.git_monitor - INFO - Checking repository for new commits (interval: 15s)",
    "2025-12-21 11:41:01,736 - services.web_repo_monitor - INFO - No new commits found",
    "2025-12-21 11:40:57,579 - services.web_repo_monitor - INFO - Checking web repository for new commits (interval: 15s)",
    "2025-12-21 11:40:54,704 - services.git_monitor - INFO - No new commits found",
    "2025-12-21 11:40:50,667 - services.git_monitor - INFO - Checking repository for new commits (interval: 15s)",
    "2025-12-21 11:40:42,578 - services.web_repo_monitor - INFO - No new commits found",
    "2025-12-21 11:40:38,562 - services.web_repo_monitor - INFO - Checking web repository for new commits (interval: 15s)",
    "2025-12-21 11:40:35,667 - services.git_monitor - INFO - No new commits found",
    "2025-12-21 11:40:31,361 - services.git_monitor - INFO - Checking repository for new commits (interval: 15s)",
    "2025-12-21 11:40:23,561 - services.web_repo_monitor - INFO - No new commits found",
    "2025-12-21 11:40:19,535 - services.web_repo_monitor - INFO - Checking web repository for new commits (interval: 15s)",
    "2025-12-21 11:40:16,360 - services.git_monitor - INFO - No new commits found",
    "2025-12-21 11:40:12,186 - services.git_monitor - INFO - Checking repository for new commits (interval: 15s)",
    "2025-12-21 11:40:04,535 - services.web_repo_monitor - INFO - No new commits found"
  ]
}