{
  "timestamp": "2025-12-21T11:57:51.832964+00:00",
  "webhook_server": {
    "online": true,
    "health": {
      "last_heartbeat_seconds_ago": 60.2,
      "last_heartbeat_timestamp": "2025-12-21T11:56:51.587795+00:00"
    },
    "pipeline_status": null,
    "error": null
  },
  "system": {
    "uptime_seconds": 157063.11,
    "cpu_percent": 0.0,
    "memory_percent": 10.0,
    "disk_percent": 19.8,
    "disk_free_gb": 44.723270416259766,
    "timestamp": "2025-12-21T06:57:51.833429"
  },
  "activity": {
    "last_report": {
      "filename": "report_20251219_234607.html",
      "timestamp": "2025-12-19T18:46:20.068596"
    },
    "last_pipeline_run": null,
    "total_reports": 25
  },
  "recent_log": [
    "2025-12-21 06:57:51,618 - services.git_monitor - INFO - No new commits found",
    "2025-12-21 06:57:47,291 - services.git_monitor - INFO - Checking repository for new commits (interval: 15s)",
    "2025-12-21 06:57:41,794 - services.web_repo_monitor - INFO - No new commits found",
    "2025-12-21 06:57:37,563 - services.web_repo_monitor - INFO - Checking web repository for new commits (interval: 15s)",
    "2025-12-21 06:57:32,291 - services.git_monitor - INFO - No new commits found",
    "2025-12-21 06:57:28,271 - services.git_monitor - INFO - Checking repository for new commits (interval: 15s)",
    "2025-12-21 06:57:22,562 - services.web_repo_monitor - INFO - No new commits found",
    "2025-12-21 06:57:18,551 - services.web_repo_monitor - INFO - Checking web repository for new commits (interval: 15s)",
    "2025-12-21 06:57:13,270 - services.git_monitor - INFO - No new commits found",
    "2025-12-21 06:57:09,020 - services.git_monitor - INFO - Checking repository for new commits (interval: 15s)",
    "2025-12-21 06:57:03,550 - services.web_repo_monitor - INFO - No new commits found",
    "2025-12-21 06:56:59,331 - services.web_repo_monitor - INFO - Checking web repository for new commits (interval: 15s)",
    "2025-12-21 06:56:54,019 - services.git_monitor - INFO - No new commits found",
    "2025-12-21 06:56:50,057 - services.git_monitor - INFO - Checking repository for new commits (interval: 15s)",
    "2025-12-21 06:56:44,330 - services.web_repo_monitor - INFO - No new commits found",
    "2025-12-21 06:56:40,116 - services.web_repo_monitor - INFO - Checking web repository for new commits (interval: 15s)",
    "2025-12-21 06:56:35,057 - services.git_monitor - INFO - No new commits found",
    "2025-12-21 06:56:30,994 - services.git_monitor - INFO - Checking repository for new commits (interval: 15s)",
    "2025-12-21 06:56:25,116 - services.web_repo_monitor - INFO - No new commits found",
    "2025-12-21 06:56:20,937 - services.web_repo_monitor - INFO - Checking web repository for new commits (interval: 15s)"
  ]
}